builddsl/__init__.py
builddsl/__main__.py
builddsl/_execute.py
builddsl/_rewriter.py
builddsl/_runtime.py
builddsl/_transpiler.py
builddsl/_util.py
builddsl/ast_utils.py
builddsl/py.typed
builddsl-1.0.1.dist-info/LICENSE
builddsl-1.0.1.dist-info/METADATA
builddsl-1.0.1.dist-info/WHEEL
builddsl-1.0.1.dist-info/RECORD
